mediamovarr/__init__.py
mediamovarr/__main__.py
mediamovarr/classify.py
mediamovarr/confidence_rules.py
mediamovarr/config.py
mediamovarr/database.py
mediamovarr/discovery.py
mediamovarr/mover.py
mediamovarr/renamer.py
mediamovarr/tmdb_client.py
mediamovarr-1.0.1.dist-info/licenses/LICENSE
mediamovarr-1.0.1.dist-info/METADATA
mediamovarr-1.0.1.dist-info/WHEEL
mediamovarr-1.0.1.dist-info/entry_points.txt
mediamovarr-1.0.1.dist-info/top_level.txt
mediamovarr-1.0.1.dist-info/RECORD
